versioneer.py
knowlify/__init__.py
knowlify/__main__.py
knowlify/_version.py
knowlify/config.py
knowlify/engine.py
knowlify/microserver.py
knowlify/parser.py
knowlify/worker.py
knowlify-0.5.3.dist-info/DESCRIPTION.rst
knowlify-0.5.3.dist-info/METADATA
knowlify-0.5.3.dist-info/RECORD
knowlify-0.5.3.dist-info/WHEEL
knowlify-0.5.3.dist-info/entry_points.txt
knowlify-0.5.3.dist-info/metadata.json
knowlify-0.5.3.dist-info/top_level.txt
