Metadata-Version: 2.0
Name: knowlify
Version: 0.5.3
Summary: Add context dependent information to a html file
Home-page: https://github.com/LotannaEzenwa/knowlify
Author: Lotanna Ezenwa
Author-email: lota.ezenwa@gmail.com
License: MIT
Platform: UNKNOWN
Requires-Dist: click
Requires-Dist: flake8
Requires-Dist: lxml
Requires-Dist: nltk
Requires-Dist: nose
Requires-Dist: requests
Requires-Dist: sphinx
Requires-Dist: versioneer
